fibrouspy/__init__.py
fibrouspy/core.py
fibrouspy/exceptions.py
fibrouspy/models/__init__.py
fibrouspy/models/enums.py
fibrouspy/models/route.py
fibrouspy/models/token.py
fibrouspy/utils/__init__.py
fibrouspy/utils/approve_helper.py
fibrouspy/utils/route_helper.py
fibrouspy-0.1.0.dist-info/LICENSE
fibrouspy-0.1.0.dist-info/METADATA
fibrouspy-0.1.0.dist-info/WHEEL
fibrouspy-0.1.0.dist-info/top_level.txt
fibrouspy-0.1.0.dist-info/RECORD
