Metadata-Version: 2.1
Name: fibrouspy
Version: 0.1.0
Summary: Fibrous Finance Python Client.
Home-page: https://github.com/hkey0/fibrous-py
Author: hkey
Classifier: Programming Language :: Python :: 3
Classifier: License :: OSI Approved :: MIT License
Classifier: Operating System :: OS Independent
License-File: LICENSE
Requires-Dist: requests
Requires-Dist: starknet-py
Requires-Dist: pydantic
Provides-Extra: dev
Requires-Dist: pytest >=6.0.0 ; extra == 'dev'
